{"nodes": [{"id": "home_pedro_openems_src_engine_ecu_sched_cpp", "label": "ecu_sched.cpp", "file_type": "code", "source_file": "src/engine/ecu_sched.cpp", "source_location": "L1"}, {"id": "engine_ecu_sched_gpio_set_af", "label": "gpio_set_af()", "file_type": "code", "source_file": "src/engine/ecu_sched.cpp", "source_location": "L124"}, {"id": "engine_ecu_sched_enter_critical", "label": "enter_critical()", "file_type": "code", "source_file": "src/engine/ecu_sched.cpp", "source_location": "L193"}, {"id": "engine_ecu_sched_exit_critical", "label": "exit_critical()", "file_type": "code", "source_file": "src/engine/ecu_sched.cpp", "source_location": "L200"}, {"id": "engine_ecu_sched_scheduler_counter", "label": "scheduler_counter()", "file_type": "code", "source_file": "src/engine/ecu_sched.cpp", "source_location": "L207"}, {"id": "engine_ecu_sched_stm32_inj_tim_ch", "label": "stm32_inj_tim_ch()", "file_type": "code", "source_file": "src/engine/ecu_sched.cpp", "source_location": "L212"}, {"id": "engine_ecu_sched_inj_ch_to_cyl_bit", "label": "inj_ch_to_cyl_bit()", "file_type": "code", "source_file": "src/engine/ecu_sched.cpp", "source_location": "L225"}, {"id": "engine_ecu_sched_ign_ch_to_cyl_bit", "label": "ign_ch_to_cyl_bit()", "file_type": "code", "source_file": "src/engine/ecu_sched.cpp", "source_location": "L237"}, {"id": "engine_ecu_sched_stm32_ign_tim_ch", "label": "stm32_ign_tim_ch()", "file_type": "code", "source_file": "src/engine/ecu_sched.cpp", "source_location": "L248"}, {"id": "engine_ecu_sched_stm32_tim_ccr", "label": "stm32_tim_ccr()", "file_type": "code", "source_file": "src/engine/ecu_sched.cpp", "source_location": "L259"}, {"id": "engine_ecu_sched_stm32_tim_cc_flag", "label": "stm32_tim_cc_flag()", "file_type": "code", "source_file": "src/engine/ecu_sched.cpp", "source_location": "L277"}, {"id": "engine_ecu_sched_stm32_write_oc_mode", "label": "stm32_write_oc_mode()", "file_type": "code", "source_file": "src/engine/ecu_sched.cpp", "source_location": "L282"}, {"id": "engine_ecu_sched_stm32_set_oc_mode", "label": "stm32_set_oc_mode()", "file_type": "code", "source_file": "src/engine/ecu_sched.cpp", "source_location": "L307"}, {"id": "engine_ecu_sched_stm32_force_oc", "label": "stm32_force_oc()", "file_type": "code", "source_file": "src/engine/ecu_sched.cpp", "source_location": "L316"}, {"id": "engine_ecu_sched_sanitize_runtime_calibration", "label": "sanitize_runtime_calibration()", "file_type": "code", "source_file": "src/engine/ecu_sched.cpp", "source_location": "L325"}, {"id": "engine_ecu_sched_force_output", "label": "force_output()", "file_type": "code", "source_file": "src/engine/ecu_sched.cpp", "source_location": "L337"}, {"id": "engine_ecu_sched_arm_channel", "label": "arm_channel()", "file_type": "code", "source_file": "src/engine/ecu_sched.cpp", "source_location": "L345"}, {"id": "engine_ecu_sched_clear_all_events_and_drive_safe_outputs", "label": "clear_all_events_and_drive_safe_outputs()", "file_type": "code", "source_file": "src/engine/ecu_sched.cpp", "source_location": "L453"}, {"id": "engine_ecu_sched_angle_to_tooth_event", "label": "angle_to_tooth_event()", "file_type": "code", "source_file": "src/engine/ecu_sched.cpp", "source_location": "L466"}, {"id": "engine_ecu_sched_engine_angle_to_trigger_angle", "label": "engine_angle_to_trigger_angle()", "file_type": "code", "source_file": "src/engine/ecu_sched.cpp", "source_location": "L478"}, {"id": "engine_ecu_sched_table_add", "label": "table_add()", "file_type": "code", "source_file": "src/engine/ecu_sched.cpp", "source_location": "L488"}, {"id": "engine_ecu_sched_ecu_hardware_init", "label": "ECU_Hardware_Init()", "file_type": "code", "source_file": "src/engine/ecu_sched.cpp", "source_location": "L505"}, {"id": "engine_ecu_sched_ticks_to_cycle_degrees", "label": "ticks_to_cycle_degrees()", "file_type": "code", "source_file": "src/engine/ecu_sched.cpp", "source_location": "L544"}, {"id": "engine_ecu_sched_clamp_inj_pw_to_ivc", "label": "clamp_inj_pw_to_ivc()", "file_type": "code", "source_file": "src/engine/ecu_sched.cpp", "source_location": "L554"}, {"id": "engine_ecu_sched_calculate_sequential_cycle", "label": "Calculate_Sequential_Cycle()", "file_type": "code", "source_file": "src/engine/ecu_sched.cpp", "source_location": "L562"}, {"id": "ckpsnapshot", "label": "CkpSnapshot", "file_type": "code", "source_file": "src/engine/ecu_sched.cpp", "source_location": "L562"}, {"id": "engine_ecu_sched_calculate_presync_revolution", "label": "calculate_presync_revolution()", "file_type": "code", "source_file": "src/engine/ecu_sched.cpp", "source_location": "L639"}, {"id": "engine_ecu_sched_ecu_sched_commit_calibration", "label": "ecu_sched_commit_calibration()", "file_type": "code", "source_file": "src/engine/ecu_sched.cpp", "source_location": "L683"}, {"id": "engine_ecu_sched_ecu_sched_set_advance_deg", "label": "ecu_sched_set_advance_deg()", "file_type": "code", "source_file": "src/engine/ecu_sched.cpp", "source_location": "L692"}, {"id": "engine_ecu_sched_ecu_sched_set_dwell_ticks", "label": "ecu_sched_set_dwell_ticks()", "file_type": "code", "source_file": "src/engine/ecu_sched.cpp", "source_location": "L693"}, {"id": "engine_ecu_sched_ecu_sched_set_inj_pw_ticks", "label": "ecu_sched_set_inj_pw_ticks()", "file_type": "code", "source_file": "src/engine/ecu_sched.cpp", "source_location": "L694"}, {"id": "engine_ecu_sched_ecu_sched_set_soi_lead_deg", "label": "ecu_sched_set_soi_lead_deg()", "file_type": "code", "source_file": "src/engine/ecu_sched.cpp", "source_location": "L695"}, {"id": "engine_ecu_sched_ecu_sched_set_presync_enable", "label": "ecu_sched_set_presync_enable()", "file_type": "code", "source_file": "src/engine/ecu_sched.cpp", "source_location": "L696"}, {"id": "engine_ecu_sched_ecu_sched_set_presync_inj_mode", "label": "ecu_sched_set_presync_inj_mode()", "file_type": "code", "source_file": "src/engine/ecu_sched.cpp", "source_location": "L697"}, {"id": "engine_ecu_sched_ecu_sched_set_presync_ign_mode", "label": "ecu_sched_set_presync_ign_mode()", "file_type": "code", "source_file": "src/engine/ecu_sched.cpp", "source_location": "L698"}, {"id": "engine_ecu_sched_ecu_sched_set_ivc", "label": "ecu_sched_set_ivc()", "file_type": "code", "source_file": "src/engine/ecu_sched.cpp", "source_location": "L699"}, {"id": "engine_ecu_sched_ecu_sched_ivc_clamp_count", "label": "ecu_sched_ivc_clamp_count()", "file_type": "code", "source_file": "src/engine/ecu_sched.cpp", "source_location": "L700"}, {"id": "engine_ecu_sched_ecu_sched_dwell_watchdog", "label": "ecu_sched_dwell_watchdog()", "file_type": "code", "source_file": "src/engine/ecu_sched.cpp", "source_location": "L702"}, {"id": "engine_ecu_sched_ecu_sched_dwell_watchdog_count", "label": "ecu_sched_dwell_watchdog_count()", "file_type": "code", "source_file": "src/engine/ecu_sched.cpp", "source_location": "L725"}, {"id": "engine_ecu_sched_ecu_sched_reset_diagnostic_counters", "label": "ecu_sched_reset_diagnostic_counters()", "file_type": "code", "source_file": "src/engine/ecu_sched.cpp", "source_location": "L727"}, {"id": "engine_ecu_sched_ecu_sched_fire_prime_pulse", "label": "ecu_sched_fire_prime_pulse()", "file_type": "code", "source_file": "src/engine/ecu_sched.cpp", "source_location": "L737"}, {"id": "engine_ecu_sched_ecu_sched_set_mspark", "label": "ecu_sched_set_mspark()", "file_type": "code", "source_file": "src/engine/ecu_sched.cpp", "source_location": "L747"}, {"id": "engine_ecu_sched_ecu_sched_set_inj_inhibit_mask", "label": "ecu_sched_set_inj_inhibit_mask()", "file_type": "code", "source_file": "src/engine/ecu_sched.cpp", "source_location": "L755"}, {"id": "engine_ecu_sched_ecu_sched_get_inj_inhibit_mask", "label": "ecu_sched_get_inj_inhibit_mask()", "file_type": "code", "source_file": "src/engine/ecu_sched.cpp", "source_location": "L760"}, {"id": "engine_ecu_sched_ecu_sched_set_ign_inhibit_mask", "label": "ecu_sched_set_ign_inhibit_mask()", "file_type": "code", "source_file": "src/engine/ecu_sched.cpp", "source_location": "L762"}, {"id": "engine_ecu_sched_ecu_sched_get_ign_inhibit_mask", "label": "ecu_sched_get_ign_inhibit_mask()", "file_type": "code", "source_file": "src/engine/ecu_sched.cpp", "source_location": "L767"}, {"id": "engine_ecu_sched_ecu_sched_on_tooth_hook", "label": "ecu_sched_on_tooth_hook()", "file_type": "code", "source_file": "src/engine/ecu_sched.cpp", "source_location": "L770"}, {"id": "engine_ecu_sched_schedule_on_tooth", "label": "schedule_on_tooth()", "file_type": "code", "source_file": "src/engine/ecu_sched.cpp", "source_location": "L815"}, {"id": "engine_ecu_sched_ecu_sched_test_reset", "label": "ecu_sched_test_reset()", "file_type": "code", "source_file": "src/engine/ecu_sched.cpp", "source_location": "L819"}, {"id": "engine_ecu_sched_ecu_sched_test_angle_table_size", "label": "ecu_sched_test_angle_table_size()", "file_type": "code", "source_file": "src/engine/ecu_sched.cpp", "source_location": "L831"}, {"id": "engine_ecu_sched_ecu_sched_test_get_angle_event", "label": "ecu_sched_test_get_angle_event()", "file_type": "code", "source_file": "src/engine/ecu_sched.cpp", "source_location": "L832"}, {"id": "engine_ecu_sched_ecu_sched_test_set_advance_deg", "label": "ecu_sched_test_set_advance_deg()", "file_type": "code", "source_file": "src/engine/ecu_sched.cpp", "source_location": "L837"}, {"id": "engine_ecu_sched_ecu_sched_test_set_dwell_ticks", "label": "ecu_sched_test_set_dwell_ticks()", "file_type": "code", "source_file": "src/engine/ecu_sched.cpp", "source_location": "L838"}, {"id": "engine_ecu_sched_ecu_sched_test_set_inj_pw_ticks", "label": "ecu_sched_test_set_inj_pw_ticks()", "file_type": "code", "source_file": "src/engine/ecu_sched.cpp", "source_location": "L839"}, {"id": "engine_ecu_sched_ecu_sched_test_set_soi_lead_deg", "label": "ecu_sched_test_set_soi_lead_deg()", "file_type": "code", "source_file": "src/engine/ecu_sched.cpp", "source_location": "L840"}, {"id": "engine_ecu_sched_ecu_sched_test_get_advance_deg", "label": "ecu_sched_test_get_advance_deg()", "file_type": "code", "source_file": "src/engine/ecu_sched.cpp", "source_location": "L841"}, {"id": "engine_ecu_sched_ecu_sched_test_get_dwell_ticks", "label": "ecu_sched_test_get_dwell_ticks()", "file_type": "code", "source_file": "src/engine/ecu_sched.cpp", "source_location": "L842"}, {"id": "engine_ecu_sched_ecu_sched_test_get_inj_pw_ticks", "label": "ecu_sched_test_get_inj_pw_ticks()", "file_type": "code", "source_file": "src/engine/ecu_sched.cpp", "source_location": "L843"}, {"id": "engine_ecu_sched_ecu_sched_test_get_soi_lead_deg", "label": "ecu_sched_test_get_soi_lead_deg()", "file_type": "code", "source_file": "src/engine/ecu_sched.cpp", "source_location": "L844"}, {"id": "engine_ecu_sched_ecu_sched_test_get_calibration_clamp_count", "label": "ecu_sched_test_get_calibration_clamp_count()", "file_type": "code", "source_file": "src/engine/ecu_sched.cpp", "source_location": "L845"}, {"id": "engine_ecu_sched_ecu_sched_test_get_cycle_schedule_drop_count", "label": "ecu_sched_test_get_cycle_schedule_drop_count()", "file_type": "code", "source_file": "src/engine/ecu_sched.cpp", "source_location": "L846"}, {"id": "engine_ecu_sched_ecu_sched_test_get_late_event_count", "label": "ecu_sched_test_get_late_event_count()", "file_type": "code", "source_file": "src/engine/ecu_sched.cpp", "source_location": "L847"}, {"id": "engine_ecu_sched_ecu_sched_test_set_ivc", "label": "ecu_sched_test_set_ivc()", "file_type": "code", "source_file": "src/engine/ecu_sched.cpp", "source_location": "L848"}, {"id": "engine_ecu_sched_ecu_sched_test_get_ivc_clamp_count", "label": "ecu_sched_test_get_ivc_clamp_count()", "file_type": "code", "source_file": "src/engine/ecu_sched.cpp", "source_location": "L849"}, {"id": "engine_ecu_sched_ecu_sched_test_set_mspark", "label": "ecu_sched_test_set_mspark()", "file_type": "code", "source_file": "src/engine/ecu_sched.cpp", "source_location": "L850"}, {"id": "engine_ecu_sched_ecu_sched_test_get_mspark_count", "label": "ecu_sched_test_get_mspark_count()", "file_type": "code", "source_file": "src/engine/ecu_sched.cpp", "source_location": "L853"}, {"id": "engine_ecu_sched_ecu_sched_test_set_tim8_cnt", "label": "ecu_sched_test_set_tim8_cnt()", "file_type": "code", "source_file": "src/engine/ecu_sched.cpp", "source_location": "L854"}, {"id": "engine_ecu_sched_ecu_sched_test_set_tim2_cnt", "label": "ecu_sched_test_set_tim2_cnt()", "file_type": "code", "source_file": "src/engine/ecu_sched.cpp", "source_location": "L855"}, {"id": "engine_ecu_sched_ecu_sched_test_reset_ccr", "label": "ecu_sched_test_reset_ccr()", "file_type": "code", "source_file": "src/engine/ecu_sched.cpp", "source_location": "L856"}, {"id": "engine_ecu_sched_ecu_sched_test_get_tim8_ccr", "label": "ecu_sched_test_get_tim8_ccr()", "file_type": "code", "source_file": "src/engine/ecu_sched.cpp", "source_location": "L860"}], "edges": [{"source": "home_pedro_openems_src_engine_ecu_sched_cpp", "target": "ecu_sched", "relation": "imports", "context": "import", "confidence": "EXTRACTED", "source_file": "src/engine/ecu_sched.cpp", "source_location": "L1", "weight": 1.0}, {"source": "home_pedro_openems_src_engine_ecu_sched_cpp", "target": "ckp", "relation": "imports", "context": "import", "confidence": "EXTRACTED", "source_file": "src/engine/ecu_sched.cpp", "source_location": "L2", "weight": 1.0}, {"source": "home_pedro_openems_src_engine_ecu_sched_cpp", "target": "engine_config", "relation": "imports", "context": "import", "confidence": "EXTRACTED", "source_file": "src/engine/ecu_sched.cpp", "source_location": "L3", "weight": 1.0}, {"source": "home_pedro_openems_src_engine_ecu_sched_cpp", "target": "constants", "relation": "imports", "context": "import", "confidence": "EXTRACTED", "source_file": "src/engine/ecu_sched.cpp", "source_location": "L4", "weight": 1.0}, {"source": "home_pedro_openems_src_engine_ecu_sched_cpp", "target": "knock", "relation": "imports", "context": "import", "confidence": "EXTRACTED", "source_file": "src/engine/ecu_sched.cpp", "source_location": "L5", "weight": 1.0}, {"source": "home_pedro_openems_src_engine_ecu_sched_cpp", "target": "calibration", "relation": "imports", "context": "import", "confidence": "EXTRACTED", "source_file": "src/engine/ecu_sched.cpp", "source_location": "L6", "weight": 1.0}, {"source": "home_pedro_openems_src_engine_ecu_sched_cpp", "target": "regs", "relation": "imports", "context": "import", "confidence": "EXTRACTED", "source_file": "src/engine/ecu_sched.cpp", "source_location": "L7", "weight": 1.0}, {"source": "home_pedro_openems_src_engine_ecu_sched_cpp", "target": "critical_section", "relation": "imports", "context": "import", "confidence": "EXTRACTED", "source_file": "src/engine/ecu_sched.cpp", "source_location": "L8", "weight": 1.0}, {"source": "home_pedro_openems_src_engine_ecu_sched_cpp", "target": "stddef", "relation": "imports", "context": "import", "confidence": "EXTRACTED", "source_file": "src/engine/ecu_sched.cpp", "source_location": "L10", "weight": 1.0}, {"source": "home_pedro_openems_src_engine_ecu_sched_cpp", "target": "stdint", "relation": "imports", "context": "import", "confidence": "EXTRACTED", "source_file": "src/engine/ecu_sched.cpp", "source_location": "L11", "weight": 1.0}, {"source": "home_pedro_openems_src_engine_ecu_sched_cpp", "target": "engine_ecu_sched_gpio_set_af", "relation": "contains", "confidence": "EXTRACTED", "source_file": "src/engine/ecu_sched.cpp", "source_location": "L124", "weight": 1.0}, {"source": "home_pedro_openems_src_engine_ecu_sched_cpp", "target": "engine_ecu_sched_enter_critical", "relation": "contains", "confidence": "EXTRACTED", "source_file": "src/engine/ecu_sched.cpp", "source_location": "L193", "weight": 1.0}, {"source": "home_pedro_openems_src_engine_ecu_sched_cpp", "target": "engine_ecu_sched_exit_critical", "relation": "contains", "confidence": "EXTRACTED", "source_file": "src/engine/ecu_sched.cpp", "source_location": "L200", "weight": 1.0}, {"source": "home_pedro_openems_src_engine_ecu_sched_cpp", "target": "engine_ecu_sched_scheduler_counter", "relation": "contains", "confidence": "EXTRACTED", "source_file": "src/engine/ecu_sched.cpp", "source_location": "L207", "weight": 1.0}, {"source": "home_pedro_openems_src_engine_ecu_sched_cpp", "target": "engine_ecu_sched_stm32_inj_tim_ch", "relation": "contains", "confidence": "EXTRACTED", "source_file": "src/engine/ecu_sched.cpp", "source_location": "L212", "weight": 1.0}, {"source": "home_pedro_openems_src_engine_ecu_sched_cpp", "target": "engine_ecu_sched_inj_ch_to_cyl_bit", "relation": "contains", "confidence": "EXTRACTED", "source_file": "src/engine/ecu_sched.cpp", "source_location": "L225", "weight": 1.0}, {"source": "home_pedro_openems_src_engine_ecu_sched_cpp", "target": "engine_ecu_sched_ign_ch_to_cyl_bit", "relation": "contains", "confidence": "EXTRACTED", "source_file": "src/engine/ecu_sched.cpp", "source_location": "L237", "weight": 1.0}, {"source": "home_pedro_openems_src_engine_ecu_sched_cpp", "target": "engine_ecu_sched_stm32_ign_tim_ch", "relation": "contains", "confidence": "EXTRACTED", "source_file": "src/engine/ecu_sched.cpp", "source_location": "L248", "weight": 1.0}, {"source": "home_pedro_openems_src_engine_ecu_sched_cpp", "target": "engine_ecu_sched_stm32_tim_ccr", "relation": "contains", "confidence": "EXTRACTED", "source_file": "src/engine/ecu_sched.cpp", "source_location": "L259", "weight": 1.0}, {"source": "home_pedro_openems_src_engine_ecu_sched_cpp", "target": "engine_ecu_sched_stm32_tim_cc_flag", "relation": "contains", "confidence": "EXTRACTED", "source_file": "src/engine/ecu_sched.cpp", "source_location": "L277", "weight": 1.0}, {"source": "home_pedro_openems_src_engine_ecu_sched_cpp", "target": "engine_ecu_sched_stm32_write_oc_mode", "relation": "contains", "confidence": "EXTRACTED", "source_file": "src/engine/ecu_sched.cpp", "source_location": "L282", "weight": 1.0}, {"source": "home_pedro_openems_src_engine_ecu_sched_cpp", "target": "engine_ecu_sched_stm32_set_oc_mode", "relation": "contains", "confidence": "EXTRACTED", "source_file": "src/engine/ecu_sched.cpp", "source_location": "L307", "weight": 1.0}, {"source": "home_pedro_openems_src_engine_ecu_sched_cpp", "target": "engine_ecu_sched_stm32_force_oc", "relation": "contains", "confidence": "EXTRACTED", "source_file": "src/engine/ecu_sched.cpp", "source_location": "L316", "weight": 1.0}, {"source": "home_pedro_openems_src_engine_ecu_sched_cpp", "target": "engine_ecu_sched_sanitize_runtime_calibration", "relation": "contains", "confidence": "EXTRACTED", "source_file": "src/engine/ecu_sched.cpp", "source_location": "L325", "weight": 1.0}, {"source": "home_pedro_openems_src_engine_ecu_sched_cpp", "target": "engine_ecu_sched_force_output", "relation": "contains", "confidence": "EXTRACTED", "source_file": "src/engine/ecu_sched.cpp", "source_location": "L337", "weight": 1.0}, {"source": "home_pedro_openems_src_engine_ecu_sched_cpp", "target": "engine_ecu_sched_arm_channel", "relation": "contains", "confidence": "EXTRACTED", "source_file": "src/engine/ecu_sched.cpp", "source_location": "L345", "weight": 1.0}, {"source": "home_pedro_openems_src_engine_ecu_sched_cpp", "target": "engine_ecu_sched_clear_all_events_and_drive_safe_outputs", "relation": "contains", "confidence": "EXTRACTED", "source_file": "src/engine/ecu_sched.cpp", "source_location": "L453", "weight": 1.0}, {"source": "home_pedro_openems_src_engine_ecu_sched_cpp", "target": "engine_ecu_sched_angle_to_tooth_event", "relation": "contains", "confidence": "EXTRACTED", "source_file": "src/engine/ecu_sched.cpp", "source_location": "L466", "weight": 1.0}, {"source": "home_pedro_openems_src_engine_ecu_sched_cpp", "target": "engine_ecu_sched_engine_angle_to_trigger_angle", "relation": "contains", "confidence": "EXTRACTED", "source_file": "src/engine/ecu_sched.cpp", "source_location": "L478", "weight": 1.0}, {"source": "home_pedro_openems_src_engine_ecu_sched_cpp", "target": "engine_ecu_sched_table_add", "relation": "contains", "confidence": "EXTRACTED", "source_file": "src/engine/ecu_sched.cpp", "source_location": "L488", "weight": 1.0}, {"source": "home_pedro_openems_src_engine_ecu_sched_cpp", "target": "engine_ecu_sched_ecu_hardware_init", "relation": "contains", "confidence": "EXTRACTED", "source_file": "src/engine/ecu_sched.cpp", "source_location": "L505", "weight": 1.0}, {"source": "home_pedro_openems_src_engine_ecu_sched_cpp", "target": "engine_ecu_sched_ticks_to_cycle_degrees", "relation": "contains", "confidence": "EXTRACTED", "source_file": "src/engine/ecu_sched.cpp", "source_location": "L544", "weight": 1.0}, {"source": "home_pedro_openems_src_engine_ecu_sched_cpp", "target": "engine_ecu_sched_clamp_inj_pw_to_ivc", "relation": "contains", "confidence": "EXTRACTED", "source_file": "src/engine/ecu_sched.cpp", "source_location": "L554", "weight": 1.0}, {"source": "home_pedro_openems_src_engine_ecu_sched_cpp", "target": "engine_ecu_sched_calculate_sequential_cycle", "relation": "contains", "confidence": "EXTRACTED", "source_file": "src/engine/ecu_sched.cpp", "source_location": "L562", "weight": 1.0}, {"source": "engine_ecu_sched_calculate_sequential_cycle", "target": "ckpsnapshot", "relation": "references", "confidence": "EXTRACTED", "source_file": "src/engine/ecu_sched.cpp", "source_location": "L562", "weight": 1.0, "context": "parameter_type"}, {"source": "home_pedro_openems_src_engine_ecu_sched_cpp", "target": "engine_ecu_sched_calculate_presync_revolution", "relation": "contains", "confidence": "EXTRACTED", "source_file": "src/engine/ecu_sched.cpp", "source_location": "L639", "weight": 1.0}, {"source": "engine_ecu_sched_calculate_presync_revolution", "target": "ckpsnapshot", "relation": "references", "confidence": "EXTRACTED", "source_file": "src/engine/ecu_sched.cpp", "source_location": "L639", "weight": 1.0, "context": "parameter_type"}, {"source": "home_pedro_openems_src_engine_ecu_sched_cpp", "target": "engine_ecu_sched_ecu_sched_commit_calibration", "relation": "contains", "confidence": "EXTRACTED", "source_file": "src/engine/ecu_sched.cpp", "source_location": "L683", "weight": 1.0}, {"source": "home_pedro_openems_src_engine_ecu_sched_cpp", "target": "engine_ecu_sched_ecu_sched_set_advance_deg", "relation": "contains", "confidence": "EXTRACTED", "source_file": "src/engine/ecu_sched.cpp", "source_location": "L692", "weight": 1.0}, {"source": "home_pedro_openems_src_engine_ecu_sched_cpp", "target": "engine_ecu_sched_ecu_sched_set_dwell_ticks", "relation": "contains", "confidence": "EXTRACTED", "source_file": "src/engine/ecu_sched.cpp", "source_location": "L693", "weight": 1.0}, {"source": "home_pedro_openems_src_engine_ecu_sched_cpp", "target": "engine_ecu_sched_ecu_sched_set_inj_pw_ticks", "relation": "contains", "confidence": "EXTRACTED", "source_file": "src/engine/ecu_sched.cpp", "source_location": "L694", "weight": 1.0}, {"source": "home_pedro_openems_src_engine_ecu_sched_cpp", "target": "engine_ecu_sched_ecu_sched_set_soi_lead_deg", "relation": "contains", "confidence": "EXTRACTED", "source_file": "src/engine/ecu_sched.cpp", "source_location": "L695", "weight": 1.0}, {"source": "home_pedro_openems_src_engine_ecu_sched_cpp", "target": "engine_ecu_sched_ecu_sched_set_presync_enable", "relation": "contains", "confidence": "EXTRACTED", "source_file": "src/engine/ecu_sched.cpp", "source_location": "L696", "weight": 1.0}, {"source": "home_pedro_openems_src_engine_ecu_sched_cpp", "target": "engine_ecu_sched_ecu_sched_set_presync_inj_mode", "relation": "contains", "confidence": "EXTRACTED", "source_file": "src/engine/ecu_sched.cpp", "source_location": "L697", "weight": 1.0}, {"source": "home_pedro_openems_src_engine_ecu_sched_cpp", "target": "engine_ecu_sched_ecu_sched_set_presync_ign_mode", "relation": "contains", "confidence": "EXTRACTED", "source_file": "src/engine/ecu_sched.cpp", "source_location": "L698", "weight": 1.0}, {"source": "home_pedro_openems_src_engine_ecu_sched_cpp", "target": "engine_ecu_sched_ecu_sched_set_ivc", "relation": "contains", "confidence": "EXTRACTED", "source_file": "src/engine/ecu_sched.cpp", "source_location": "L699", "weight": 1.0}, {"source": "home_pedro_openems_src_engine_ecu_sched_cpp", "target": "engine_ecu_sched_ecu_sched_ivc_clamp_count", "relation": "contains", "confidence": "EXTRACTED", "source_file": "src/engine/ecu_sched.cpp", "source_location": "L700", "weight": 1.0}, {"source": "home_pedro_openems_src_engine_ecu_sched_cpp", "target": "engine_ecu_sched_ecu_sched_dwell_watchdog", "relation": "contains", "confidence": "EXTRACTED", "source_file": "src/engine/ecu_sched.cpp", "source_location": "L702", "weight": 1.0}, {"source": "home_pedro_openems_src_engine_ecu_sched_cpp", "target": "engine_ecu_sched_ecu_sched_dwell_watchdog_count", "relation": "contains", "confidence": "EXTRACTED", "source_file": "src/engine/ecu_sched.cpp", "source_location": "L725", "weight": 1.0}, {"source": "home_pedro_openems_src_engine_ecu_sched_cpp", "target": "engine_ecu_sched_ecu_sched_reset_diagnostic_counters", "relation": "contains", "confidence": "EXTRACTED", "source_file": "src/engine/ecu_sched.cpp", "source_location": "L727", "weight": 1.0}, {"source": "home_pedro_openems_src_engine_ecu_sched_cpp", "target": "engine_ecu_sched_ecu_sched_fire_prime_pulse", "relation": "contains", "confidence": "EXTRACTED", "source_file": "src/engine/ecu_sched.cpp", "source_location": "L737", "weight": 1.0}, {"source": "home_pedro_openems_src_engine_ecu_sched_cpp", "target": "engine_ecu_sched_ecu_sched_set_mspark", "relation": "contains", "confidence": "EXTRACTED", "source_file": "src/engine/ecu_sched.cpp", "source_location": "L747", "weight": 1.0}, {"source": "home_pedro_openems_src_engine_ecu_sched_cpp", "target": "engine_ecu_sched_ecu_sched_set_inj_inhibit_mask", "relation": "contains", "confidence": "EXTRACTED", "source_file": "src/engine/ecu_sched.cpp", "source_location": "L755", "weight": 1.0}, {"source": "home_pedro_openems_src_engine_ecu_sched_cpp", "target": "engine_ecu_sched_ecu_sched_get_inj_inhibit_mask", "relation": "contains", "confidence": "EXTRACTED", "source_file": "src/engine/ecu_sched.cpp", "source_location": "L760", "weight": 1.0}, {"source": "home_pedro_openems_src_engine_ecu_sched_cpp", "target": "engine_ecu_sched_ecu_sched_set_ign_inhibit_mask", "relation": "contains", "confidence": "EXTRACTED", "source_file": "src/engine/ecu_sched.cpp", "source_location": "L762", "weight": 1.0}, {"source": "home_pedro_openems_src_engine_ecu_sched_cpp", "target": "engine_ecu_sched_ecu_sched_get_ign_inhibit_mask", "relation": "contains", "confidence": "EXTRACTED", "source_file": "src/engine/ecu_sched.cpp", "source_location": "L767", "weight": 1.0}, {"source": "home_pedro_openems_src_engine_ecu_sched_cpp", "target": "engine_ecu_sched_ecu_sched_on_tooth_hook", "relation": "contains", "confidence": "EXTRACTED", "source_file": "src/engine/ecu_sched.cpp", "source_location": "L770", "weight": 1.0}, {"source": "engine_ecu_sched_ecu_sched_on_tooth_hook", "target": "ckpsnapshot", "relation": "references", "confidence": "EXTRACTED", "source_file": "src/engine/ecu_sched.cpp", "source_location": "L770", "weight": 1.0, "context": "parameter_type"}, {"source": "home_pedro_openems_src_engine_ecu_sched_cpp", "target": "engine_ecu_sched_schedule_on_tooth", "relation": "contains", "confidence": "EXTRACTED", "source_file": "src/engine/ecu_sched.cpp", "source_location": "L815", "weight": 1.0}, {"source": "engine_ecu_sched_schedule_on_tooth", "target": "ckpsnapshot", "relation": "references", "confidence": "EXTRACTED", "source_file": "src/engine/ecu_sched.cpp", "source_location": "L815", "weight": 1.0, "context": "parameter_type"}, {"source": "home_pedro_openems_src_engine_ecu_sched_cpp", "target": "engine_ecu_sched_ecu_sched_test_reset", "relation": "contains", "confidence": "EXTRACTED", "source_file": "src/engine/ecu_sched.cpp", "source_location": "L819", "weight": 1.0}, {"source": "home_pedro_openems_src_engine_ecu_sched_cpp", "target": "engine_ecu_sched_ecu_sched_test_angle_table_size", "relation": "contains", "confidence": "EXTRACTED", "source_file": "src/engine/ecu_sched.cpp", "source_location": "L831", "weight": 1.0}, {"source": "home_pedro_openems_src_engine_ecu_sched_cpp", "target": "engine_ecu_sched_ecu_sched_test_get_angle_event", "relation": "contains", "confidence": "EXTRACTED", "source_file": "src/engine/ecu_sched.cpp", "source_location": "L832", "weight": 1.0}, {"source": "home_pedro_openems_src_engine_ecu_sched_cpp", "target": "engine_ecu_sched_ecu_sched_test_set_advance_deg", "relation": "contains", "confidence": "EXTRACTED", "source_file": "src/engine/ecu_sched.cpp", "source_location": "L837", "weight": 1.0}, {"source": "home_pedro_openems_src_engine_ecu_sched_cpp", "target": "engine_ecu_sched_ecu_sched_test_set_dwell_ticks", "relation": "contains", "confidence": "EXTRACTED", "source_file": "src/engine/ecu_sched.cpp", "source_location": "L838", "weight": 1.0}, {"source": "home_pedro_openems_src_engine_ecu_sched_cpp", "target": "engine_ecu_sched_ecu_sched_test_set_inj_pw_ticks", "relation": "contains", "confidence": "EXTRACTED", "source_file": "src/engine/ecu_sched.cpp", "source_location": "L839", "weight": 1.0}, {"source": "home_pedro_openems_src_engine_ecu_sched_cpp", "target": "engine_ecu_sched_ecu_sched_test_set_soi_lead_deg", "relation": "contains", "confidence": "EXTRACTED", "source_file": "src/engine/ecu_sched.cpp", "source_location": "L840", "weight": 1.0}, {"source": "home_pedro_openems_src_engine_ecu_sched_cpp", "target": "engine_ecu_sched_ecu_sched_test_get_advance_deg", "relation": "contains", "confidence": "EXTRACTED", "source_file": "src/engine/ecu_sched.cpp", "source_location": "L841", "weight": 1.0}, {"source": "home_pedro_openems_src_engine_ecu_sched_cpp", "target": "engine_ecu_sched_ecu_sched_test_get_dwell_ticks", "relation": "contains", "confidence": "EXTRACTED", "source_file": "src/engine/ecu_sched.cpp", "source_location": "L842", "weight": 1.0}, {"source": "home_pedro_openems_src_engine_ecu_sched_cpp", "target": "engine_ecu_sched_ecu_sched_test_get_inj_pw_ticks", "relation": "contains", "confidence": "EXTRACTED", "source_file": "src/engine/ecu_sched.cpp", "source_location": "L843", "weight": 1.0}, {"source": "home_pedro_openems_src_engine_ecu_sched_cpp", "target": "engine_ecu_sched_ecu_sched_test_get_soi_lead_deg", "relation": "contains", "confidence": "EXTRACTED", "source_file": "src/engine/ecu_sched.cpp", "source_location": "L844", "weight": 1.0}, {"source": "home_pedro_openems_src_engine_ecu_sched_cpp", "target": "engine_ecu_sched_ecu_sched_test_get_calibration_clamp_count", "relation": "contains", "confidence": "EXTRACTED", "source_file": "src/engine/ecu_sched.cpp", "source_location": "L845", "weight": 1.0}, {"source": "home_pedro_openems_src_engine_ecu_sched_cpp", "target": "engine_ecu_sched_ecu_sched_test_get_cycle_schedule_drop_count", "relation": "contains", "confidence": "EXTRACTED", "source_file": "src/engine/ecu_sched.cpp", "source_location": "L846", "weight": 1.0}, {"source": "home_pedro_openems_src_engine_ecu_sched_cpp", "target": "engine_ecu_sched_ecu_sched_test_get_late_event_count", "relation": "contains", "confidence": "EXTRACTED", "source_file": "src/engine/ecu_sched.cpp", "source_location": "L847", "weight": 1.0}, {"source": "home_pedro_openems_src_engine_ecu_sched_cpp", "target": "engine_ecu_sched_ecu_sched_test_set_ivc", "relation": "contains", "confidence": "EXTRACTED", "source_file": "src/engine/ecu_sched.cpp", "source_location": "L848", "weight": 1.0}, {"source": "home_pedro_openems_src_engine_ecu_sched_cpp", "target": "engine_ecu_sched_ecu_sched_test_get_ivc_clamp_count", "relation": "contains", "confidence": "EXTRACTED", "source_file": "src/engine/ecu_sched.cpp", "source_location": "L849", "weight": 1.0}, {"source": "home_pedro_openems_src_engine_ecu_sched_cpp", "target": "engine_ecu_sched_ecu_sched_test_set_mspark", "relation": "contains", "confidence": "EXTRACTED", "source_file": "src/engine/ecu_sched.cpp", "source_location": "L850", "weight": 1.0}, {"source": "home_pedro_openems_src_engine_ecu_sched_cpp", "target": "engine_ecu_sched_ecu_sched_test_get_mspark_count", "relation": "contains", "confidence": "EXTRACTED", "source_file": "src/engine/ecu_sched.cpp", "source_location": "L853", "weight": 1.0}, {"source": "home_pedro_openems_src_engine_ecu_sched_cpp", "target": "engine_ecu_sched_ecu_sched_test_set_tim8_cnt", "relation": "contains", "confidence": "EXTRACTED", "source_file": "src/engine/ecu_sched.cpp", "source_location": "L854", "weight": 1.0}, {"source": "home_pedro_openems_src_engine_ecu_sched_cpp", "target": "engine_ecu_sched_ecu_sched_test_set_tim2_cnt", "relation": "contains", "confidence": "EXTRACTED", "source_file": "src/engine/ecu_sched.cpp", "source_location": "L855", "weight": 1.0}, {"source": "home_pedro_openems_src_engine_ecu_sched_cpp", "target": "engine_ecu_sched_ecu_sched_test_reset_ccr", "relation": "contains", "confidence": "EXTRACTED", "source_file": "src/engine/ecu_sched.cpp", "source_location": "L856", "weight": 1.0}, {"source": "home_pedro_openems_src_engine_ecu_sched_cpp", "target": "engine_ecu_sched_ecu_sched_test_get_tim8_ccr", "relation": "contains", "confidence": "EXTRACTED", "source_file": "src/engine/ecu_sched.cpp", "source_location": "L860", "weight": 1.0}, {"source": "engine_ecu_sched_stm32_set_oc_mode", "target": "engine_ecu_sched_stm32_write_oc_mode", "relation": "calls", "context": "call", "confidence": "EXTRACTED", "source_file": "src/engine/ecu_sched.cpp", "source_location": "L309", "weight": 1.0}, {"source": "engine_ecu_sched_stm32_force_oc", "target": "engine_ecu_sched_stm32_write_oc_mode", "relation": "calls", "context": "call", "confidence": "EXTRACTED", "source_file": "src/engine/ecu_sched.cpp", "source_location": "L318", "weight": 1.0}, {"source": "engine_ecu_sched_force_output", "target": "engine_ecu_sched_stm32_inj_tim_ch", "relation": "calls", "context": "call", "confidence": "EXTRACTED", "source_file": "src/engine/ecu_sched.cpp", "source_location": "L340", "weight": 1.0}, {"source": "engine_ecu_sched_force_output", "target": "engine_ecu_sched_stm32_ign_tim_ch", "relation": "calls", "context": "call", "confidence": "EXTRACTED", "source_file": "src/engine/ecu_sched.cpp", "source_location": "L340", "weight": 1.0}, {"source": "engine_ecu_sched_force_output", "target": "engine_ecu_sched_stm32_force_oc", "relation": "calls", "context": "call", "confidence": "EXTRACTED", "source_file": "src/engine/ecu_sched.cpp", "source_location": "L342", "weight": 1.0}, {"source": "engine_ecu_sched_arm_channel", "target": "engine_ecu_sched_stm32_inj_tim_ch", "relation": "calls", "context": "call", "confidence": "EXTRACTED", "source_file": "src/engine/ecu_sched.cpp", "source_location": "L354", "weight": 1.0}, {"source": "engine_ecu_sched_arm_channel", "target": "engine_ecu_sched_stm32_ign_tim_ch", "relation": "calls", "context": "call", "confidence": "EXTRACTED", "source_file": "src/engine/ecu_sched.cpp", "source_location": "L354", "weight": 1.0}, {"source": "engine_ecu_sched_arm_channel", "target": "engine_ecu_sched_scheduler_counter", "relation": "calls", "context": "call", "confidence": "EXTRACTED", "source_file": "src/engine/ecu_sched.cpp", "source_location": "L355", "weight": 1.0}, {"source": "engine_ecu_sched_arm_channel", "target": "engine_ecu_sched_inj_ch_to_cyl_bit", "relation": "calls", "context": "call", "confidence": "EXTRACTED", "source_file": "src/engine/ecu_sched.cpp", "source_location": "L390", "weight": 1.0}, {"source": "engine_ecu_sched_arm_channel", "target": "engine_ecu_sched_ign_ch_to_cyl_bit", "relation": "calls", "context": "call", "confidence": "EXTRACTED", "source_file": "src/engine/ecu_sched.cpp", "source_location": "L398", "weight": 1.0}, {"source": "engine_ecu_sched_arm_channel", "target": "engine_ecu_sched_stm32_set_oc_mode", "relation": "calls", "context": "call", "confidence": "EXTRACTED", "source_file": "src/engine/ecu_sched.cpp", "source_location": "L428", "weight": 1.0}, {"source": "engine_ecu_sched_arm_channel", "target": "engine_ecu_sched_stm32_tim_cc_flag", "relation": "calls", "context": "call", "confidence": "EXTRACTED", "source_file": "src/engine/ecu_sched.cpp", "source_location": "L431", "weight": 1.0}, {"source": "engine_ecu_sched_arm_channel", "target": "engine_ecu_sched_stm32_tim_ccr", "relation": "calls", "context": "call", "confidence": "EXTRACTED", "source_file": "src/engine/ecu_sched.cpp", "source_location": "L438", "weight": 1.0}, {"source": "engine_ecu_sched_clear_all_events_and_drive_safe_outputs", "target": "engine_ecu_sched_force_output", "relation": "calls", "context": "call", "confidence": "EXTRACTED", "source_file": "src/engine/ecu_sched.cpp", "source_location": "L458", "weight": 1.0}, {"source": "engine_ecu_sched_ecu_hardware_init", "target": "engine_ecu_sched_gpio_set_af", "relation": "calls", "context": "call", "confidence": "EXTRACTED", "source_file": "src/engine/ecu_sched.cpp", "source_location": "L511", "weight": 1.0}, {"source": "engine_ecu_sched_ecu_hardware_init", "target": "engine_ecu_sched_clear_all_events_and_drive_safe_outputs", "relation": "calls", "context": "call", "confidence": "EXTRACTED", "source_file": "src/engine/ecu_sched.cpp", "source_location": "L541", "weight": 1.0}, {"source": "engine_ecu_sched_calculate_sequential_cycle", "target": "engine_ecu_sched_ticks_to_cycle_degrees", "relation": "calls", "context": "call", "confidence": "EXTRACTED", "source_file": "src/engine/ecu_sched.cpp", "source_location": "L573", "weight": 1.0}, {"source": "engine_ecu_sched_calculate_sequential_cycle", "target": "engine_ecu_sched_clamp_inj_pw_to_ivc", "relation": "calls", "context": "call", "confidence": "EXTRACTED", "source_file": "src/engine/ecu_sched.cpp", "source_location": "L597", "weight": 1.0}, {"source": "engine_ecu_sched_calculate_sequential_cycle", "target": "engine_ecu_sched_angle_to_tooth_event", "relation": "calls", "context": "call", "confidence": "EXTRACTED", "source_file": "src/engine/ecu_sched.cpp", "source_location": "L601", "weight": 1.0}, {"source": "engine_ecu_sched_calculate_sequential_cycle", "target": "engine_ecu_sched_engine_angle_to_trigger_angle", "relation": "calls", "context": "call", "confidence": "EXTRACTED", "source_file": "src/engine/ecu_sched.cpp", "source_location": "L601", "weight": 1.0}, {"source": "engine_ecu_sched_calculate_sequential_cycle", "target": "engine_ecu_sched_table_add", "relation": "calls", "context": "call", "confidence": "EXTRACTED", "source_file": "src/engine/ecu_sched.cpp", "source_location": "L602", "weight": 1.0}, {"source": "engine_ecu_sched_calculate_presync_revolution", "target": "engine_ecu_sched_ticks_to_cycle_degrees", "relation": "calls", "context": "call", "confidence": "EXTRACTED", "source_file": "src/engine/ecu_sched.cpp", "source_location": "L652", "weight": 1.0}, {"source": "engine_ecu_sched_calculate_presync_revolution", "target": "engine_ecu_sched_angle_to_tooth_event", "relation": "calls", "context": "call", "confidence": "EXTRACTED", "source_file": "src/engine/ecu_sched.cpp", "source_location": "L659", "weight": 1.0}, {"source": "engine_ecu_sched_calculate_presync_revolution", "target": "engine_ecu_sched_engine_angle_to_trigger_angle", "relation": "calls", "context": "call", "confidence": "EXTRACTED", "source_file": "src/engine/ecu_sched.cpp", "source_location": "L659", "weight": 1.0}, {"source": "engine_ecu_sched_calculate_presync_revolution", "target": "engine_ecu_sched_table_add", "relation": "calls", "context": "call", "confidence": "EXTRACTED", "source_file": "src/engine/ecu_sched.cpp", "source_location": "L660", "weight": 1.0}, {"source": "engine_ecu_sched_ecu_sched_commit_calibration", "target": "engine_ecu_sched_sanitize_runtime_calibration", "relation": "calls", "context": "call", "confidence": "EXTRACTED", "source_file": "src/engine/ecu_sched.cpp", "source_location": "L690", "weight": 1.0}, {"source": "engine_ecu_sched_ecu_sched_set_advance_deg", "target": "engine_ecu_sched_sanitize_runtime_calibration", "relation": "calls", "context": "call", "confidence": "EXTRACTED", "source_file": "src/engine/ecu_sched.cpp", "source_location": "L692", "weight": 1.0}, {"source": "engine_ecu_sched_ecu_sched_set_dwell_ticks", "target": "engine_ecu_sched_sanitize_runtime_calibration", "relation": "calls", "context": "call", "confidence": "EXTRACTED", "source_file": "src/engine/ecu_sched.cpp", "source_location": "L693", "weight": 1.0}, {"source": "engine_ecu_sched_ecu_sched_set_inj_pw_ticks", "target": "engine_ecu_sched_sanitize_runtime_calibration", "relation": "calls", "context": "call", "confidence": "EXTRACTED", "source_file": "src/engine/ecu_sched.cpp", "source_location": "L694", "weight": 1.0}, {"source": "engine_ecu_sched_ecu_sched_set_soi_lead_deg", "target": "engine_ecu_sched_sanitize_runtime_calibration", "relation": "calls", "context": "call", "confidence": "EXTRACTED", "source_file": "src/engine/ecu_sched.cpp", "source_location": "L695", "weight": 1.0}, {"source": "engine_ecu_sched_ecu_sched_set_presync_inj_mode", "target": "engine_ecu_sched_sanitize_runtime_calibration", "relation": "calls", "context": "call", "confidence": "EXTRACTED", "source_file": "src/engine/ecu_sched.cpp", "source_location": "L697", "weight": 1.0}, {"source": "engine_ecu_sched_ecu_sched_set_presync_ign_mode", "target": "engine_ecu_sched_sanitize_runtime_calibration", "relation": "calls", "context": "call", "confidence": "EXTRACTED", "source_file": "src/engine/ecu_sched.cpp", "source_location": "L698", "weight": 1.0}, {"source": "engine_ecu_sched_ecu_sched_dwell_watchdog", "target": "engine_ecu_sched_enter_critical", "relation": "calls", "context": "call", "confidence": "EXTRACTED", "source_file": "src/engine/ecu_sched.cpp", "source_location": "L713", "weight": 1.0}, {"source": "engine_ecu_sched_ecu_sched_dwell_watchdog", "target": "engine_ecu_sched_stm32_force_oc", "relation": "calls", "context": "call", "confidence": "EXTRACTED", "source_file": "src/engine/ecu_sched.cpp", "source_location": "L717", "weight": 1.0}, {"source": "engine_ecu_sched_ecu_sched_dwell_watchdog", "target": "engine_ecu_sched_exit_critical", "relation": "calls", "context": "call", "confidence": "EXTRACTED", "source_file": "src/engine/ecu_sched.cpp", "source_location": "L721", "weight": 1.0}, {"source": "engine_ecu_sched_ecu_sched_fire_prime_pulse", "target": "engine_ecu_sched_scheduler_counter", "relation": "calls", "context": "call", "confidence": "EXTRACTED", "source_file": "src/engine/ecu_sched.cpp", "source_location": "L742", "weight": 1.0}, {"source": "engine_ecu_sched_ecu_sched_fire_prime_pulse", "target": "engine_ecu_sched_force_output", "relation": "calls", "context": "call", "confidence": "EXTRACTED", "source_file": "src/engine/ecu_sched.cpp", "source_location": "L743", "weight": 1.0}, {"source": "engine_ecu_sched_ecu_sched_fire_prime_pulse", "target": "engine_ecu_sched_arm_channel", "relation": "calls", "context": "call", "confidence": "EXTRACTED", "source_file": "src/engine/ecu_sched.cpp", "source_location": "L744", "weight": 1.0}, {"source": "engine_ecu_sched_ecu_sched_on_tooth_hook", "target": "engine_ecu_sched_clear_all_events_and_drive_safe_outputs", "relation": "calls", "context": "call", "confidence": "EXTRACTED", "source_file": "src/engine/ecu_sched.cpp", "source_location": "L773", "weight": 1.0}, {"source": "engine_ecu_sched_ecu_sched_on_tooth_hook", "target": "engine_ecu_sched_calculate_presync_revolution", "relation": "calls", "context": "call", "confidence": "EXTRACTED", "source_file": "src/engine/ecu_sched.cpp", "source_location": "L780", "weight": 1.0}, {"source": "engine_ecu_sched_ecu_sched_on_tooth_hook", "target": "engine_ecu_sched_calculate_sequential_cycle", "relation": "calls", "context": "call", "confidence": "EXTRACTED", "source_file": "src/engine/ecu_sched.cpp", "source_location": "L783", "weight": 1.0}, {"source": "engine_ecu_sched_ecu_sched_on_tooth_hook", "target": "engine_ecu_sched_scheduler_counter", "relation": "calls", "context": "call", "confidence": "EXTRACTED", "source_file": "src/engine/ecu_sched.cpp", "source_location": "L800", "weight": 1.0}, {"source": "engine_ecu_sched_ecu_sched_on_tooth_hook", "target": "engine_ecu_sched_arm_channel", "relation": "calls", "context": "call", "confidence": "EXTRACTED", "source_file": "src/engine/ecu_sched.cpp", "source_location": "L806", "weight": 1.0}, {"source": "engine_ecu_sched_ecu_sched_test_set_advance_deg", "target": "engine_ecu_sched_ecu_sched_set_advance_deg", "relation": "calls", "context": "call", "confidence": "EXTRACTED", "source_file": "src/engine/ecu_sched.cpp", "source_location": "L837", "weight": 1.0}, {"source": "engine_ecu_sched_ecu_sched_test_set_dwell_ticks", "target": "engine_ecu_sched_ecu_sched_set_dwell_ticks", "relation": "calls", "context": "call", "confidence": "EXTRACTED", "source_file": "src/engine/ecu_sched.cpp", "source_location": "L838", "weight": 1.0}, {"source": "engine_ecu_sched_ecu_sched_test_set_inj_pw_ticks", "target": "engine_ecu_sched_ecu_sched_set_inj_pw_ticks", "relation": "calls", "context": "call", "confidence": "EXTRACTED", "source_file": "src/engine/ecu_sched.cpp", "source_location": "L839", "weight": 1.0}, {"source": "engine_ecu_sched_ecu_sched_test_set_soi_lead_deg", "target": "engine_ecu_sched_ecu_sched_set_soi_lead_deg", "relation": "calls", "context": "call", "confidence": "EXTRACTED", "source_file": "src/engine/ecu_sched.cpp", "source_location": "L840", "weight": 1.0}, {"source": "engine_ecu_sched_ecu_sched_test_set_ivc", "target": "engine_ecu_sched_ecu_sched_set_ivc", "relation": "calls", "context": "call", "confidence": "EXTRACTED", "source_file": "src/engine/ecu_sched.cpp", "source_location": "L848", "weight": 1.0}, {"source": "engine_ecu_sched_ecu_sched_test_set_mspark", "target": "engine_ecu_sched_ecu_sched_set_mspark", "relation": "calls", "context": "call", "confidence": "EXTRACTED", "source_file": "src/engine/ecu_sched.cpp", "source_location": "L851", "weight": 1.0}], "raw_calls": [{"caller_nid": "engine_ecu_sched_arm_channel", "callee": "engine::knock_window_cycle_end", "is_member_call": true, "source_file": "/home/pedro/OpenEMS/src/engine/ecu_sched.cpp", "source_location": "L419"}, {"caller_nid": "engine_ecu_sched_arm_channel", "callee": "engine::knock_window_open", "is_member_call": true, "source_file": "/home/pedro/OpenEMS/src/engine/ecu_sched.cpp", "source_location": "L420"}, {"caller_nid": "engine_ecu_sched_clear_all_events_and_drive_safe_outputs", "callee": "engine::knock_window_cycle_end", "is_member_call": true, "source_file": "/home/pedro/OpenEMS/src/engine/ecu_sched.cpp", "source_location": "L463"}, {"caller_nid": "engine_ecu_sched_ticks_to_cycle_degrees", "callee": "TOOTH_NS_TO_SCHED", "is_member_call": false, "source_file": "/home/pedro/OpenEMS/src/engine/ecu_sched.cpp", "source_location": "L546"}, {"caller_nid": "engine_ecu_sched_calculate_sequential_cycle", "callee": "engine::cfg::cyl_tdc_deg", "is_member_call": true, "source_file": "/home/pedro/OpenEMS/src/engine/ecu_sched.cpp", "source_location": "L578"}, {"caller_nid": "engine_ecu_sched_ecu_sched_on_tooth_hook", "callee": "TOOTH_NS_TO_SCHED", "is_member_call": false, "source_file": "/home/pedro/OpenEMS/src/engine/ecu_sched.cpp", "source_location": "L799"}, {"caller_nid": "engine_ecu_sched_schedule_on_tooth", "callee": "engine::ecu_sched_on_tooth_hook", "is_member_call": true, "source_file": "/home/pedro/OpenEMS/src/engine/ecu_sched.cpp", "source_location": "L815"}]}